sqlecto/__init__.py
sqlecto/converter.py
sqlecto/main.py
sqlecto/utils.py
sqlecto-0.1.0.dist-info/LICENSE
sqlecto-0.1.0.dist-info/METADATA
sqlecto-0.1.0.dist-info/WHEEL
sqlecto-0.1.0.dist-info/entry_points.txt
sqlecto-0.1.0.dist-info/RECORD
